setup.py
docs/source/HISTORY.rst
docs/source/README.rst
mr/__init__.py
mr.kangaroo.egg-info/PKG-INFO
mr.kangaroo.egg-info/SOURCES.txt
mr.kangaroo.egg-info/dependency_links.txt
mr.kangaroo.egg-info/namespace_packages.txt
mr.kangaroo.egg-info/not-zip-safe
mr.kangaroo.egg-info/requires.txt
mr.kangaroo.egg-info/top_level.txt
mr/kangaroo/__init__.py