Metadata-Version: 1.1
Name: mr.kangaroo
Version: 0.0.3
Summary: mr.kangaroo
Home-page: http://pypi.python.org/pypi/mr.kangaroo
Author: Andreas Jung
Author-email: info@zopyx.com
License: GPL
Keywords: kangaroo
Platform: UNKNOWN
Classifier: Programming Language :: Python
Classifier: Topic :: Software Development :: Libraries :: Python Modules
